[
  {
    "title": "Patience",
    "message": "La patience est une vertu qui vous sera bénéfique dans les jours à venir. Attendez le bon moment pour agir."
  },
  {
    "title": "Courage",
    "message": "Le courage n'est pas l'absence de peur, mais la capacité de la surmonter. Affrontez vos défis avec détermination."
  },
  {
    "title": "Sagesse",
    "message": "La sagesse vient de l'expérience. Écoutez les conseils des personnes qui vous entourent et apprenez de vos erreurs."
  },
  {
    "title": "Amour",
    "message": "L'amour est la force la plus puissante de l'univers. Ouvrez votre cœur aux possibilités qui se présentent à vous."
  },
  {
    "title": "Persévérance",
    "message": "La persévérance est la clé du succès. Continuez à avancer même quand le chemin semble difficile."
  },
  {
    "title": "Créativité",
    "message": "Votre créativité est votre plus grand atout. Explorez de nouvelles idées et laissez votre imagination vous guider."
  },
  {
    "title": "Équilibre",
    "message": "Cherchez l'équilibre dans tous les aspects de votre vie. Ni trop, ni trop peu - la modération est essentielle."
  },
  {
    "title": "Transformation",
    "message": "Une période de transformation s'annonce. Embrassez le changement car il vous mènera vers de nouvelles opportunités."
  },
  {
    "title": "Intuition",
    "message": "Faites confiance à votre intuition. La réponse que vous cherchez est déjà en vous."
  },
  {
    "title": "Gratitude",
    "message": "La gratitude ouvre la porte à l'abondance. Prenez le temps d'apprécier ce que vous avez déjà."
  },
  {
    "title": "Harmonie",
    "message": "Recherchez l'harmonie dans vos relations. La paix intérieure se reflète dans votre environnement."
  },
  {
    "title": "Détermination",
    "message": "Votre détermination vous mènera loin. Fixez-vous des objectifs clairs et poursuivez-les avec passion."
  },
  {
    "title": "Renouveau",
    "message": "Un nouveau chapitre de votre vie commence. Laissez derrière vous ce qui ne vous sert plus."
  },
  {
    "title": "Confiance",
    "message": "Ayez confiance en vous et en vos capacités. Vous êtes plus fort que vous ne le pensez."
  },
  {
    "title": "Sérénité",
    "message": "Trouvez la sérénité au milieu du chaos. La paix intérieure est votre refuge."
  },
  {
    "title": "Opportunité",
    "message": "Une opportunité importante se présentera bientôt. Soyez prêt à la saisir quand elle apparaîtra."
  },
  {
    "title": "Compassion",
    "message": "La compassion envers les autres commence par la compassion envers soi-même. Soyez bienveillant."
  },
  {
    "title": "Clarté",
    "message": "La clarté vient quand l'esprit est calme. Prenez le temps de vous recentrer pour voir le chemin à suivre."
  },
  {
    "title": "Abondance",
    "message": "L'abondance se manifeste de nombreuses façons. Ouvrez-vous à recevoir les bénédictions de l'univers."
  },
  {
    "title": "Résilience",
    "message": "Votre résilience est votre force. Vous avez la capacité de vous relever après chaque épreuve."
  }
]
